MelloBot/__init__.py
MelloBot/client/__init__.py
MelloBot/client/cogs/__init__.py
MelloBot/client/cogs/cosmetic_shortcuts.py
MelloBot/client/cogs/cosmetics.py
MelloBot/client/cogs/others.py
MelloBot/client/cogs/party.py
MelloBot/client/cogs/squad_assignments.py
MelloBot/client/events/__init__.py
MelloBot/client/events/friends.py
MelloBot/webserver/__init__.py
MelloBot/webserver/cosmetics.py
MelloBot/webserver/dashboard.py
MelloBot/webserver/system.py
MelloBot-9.0.2.dist-info/METADATA
MelloBot-9.0.2.dist-info/WHEEL
MelloBot-9.0.2.dist-info/top_level.txt
MelloBot-9.0.2.dist-info/RECORD
