Metadata-Version: 2.1
Name: MelloBot
Version: 9.0.2
Summary: A Multi Action Fortnite Bot with Admin Controls
Home-page: https://github.com/PirxcyFinal/MelloBot/
Author: Pirxcy
License: UNKNOWN
Platform: UNKNOWN
Classifier: Programming Language :: Python :: 3
Classifier: License :: OSI Approved :: MIT License
Classifier: Operating System :: OS Independent
Requires-Dist: sanic
Requires-Dist: flask
Requires-Dist: crayons
Requires-Dist: pycld2
Requires-Dist: fortnite-api
Requires-Dist: requests
Requires-Dist: jinja2
Requires-Dist: jaconv
Requires-Dist: colorama
Requires-Dist: fortnitepy
Requires-Dist: BenBotAsync
Requires-Dist: discord.py
Requires-Dist: FortniteAPIAsync
